LICENSE
README.md
setup.py
holiday_jp/__init__.py
holiday_jp/holiday_jp.py
holiday_jp/holidays.py
holiday_jp/test.py
holiday_jp.egg-info/PKG-INFO
holiday_jp.egg-info/SOURCES.txt
holiday_jp.egg-info/dependency_links.txt
holiday_jp.egg-info/not-zip-safe
holiday_jp.egg-info/top_level.txt