Metadata-Version: 2.1
Name: holiday-jp
Version: 22.10.31
Summary: Japanese holiday for Python
Home-page: https://github.com/LUXEYS/holiday_jp-python
Author: Luxeys
Author-email: tessier@luxeys.com
License: MIT
Platform: UNKNOWN
Classifier: Environment :: Web Environment
Classifier: Intended Audience :: Developers
Classifier: License :: OSI Approved :: MIT License
Classifier: Operating System :: OS Independent
Classifier: Programming Language :: Python :: 3.6
Classifier: Programming Language :: Python :: 3.7
Classifier: Programming Language :: Python :: 3.8
Classifier: Programming Language :: Python :: 3.9
Classifier: Programming Language :: Python :: 3.10
License-File: LICENSE
